setup.py
geepy/__init__.py
geepy/base.py
geepy/simbinCLF.py
geepy/test.py
geepy.egg-info/PKG-INFO
geepy.egg-info/SOURCES.txt
geepy.egg-info/dependency_links.txt
geepy.egg-info/not-zip-safe
geepy.egg-info/top_level.txt