Metadata-Version: 1.0
Name: geepy
Version: 0.0.1
Summary: A Python package for estimating equations
Home-page: https://github.com/hengshiyu/geepy
Author: Hengshi Yu
Author-email: hengshi@umich.edu
License: UNKNOWN
Platform: UNKNOWN
